manimlib/__init__.py
manimlib/__main__.py
manimlib/config.py
manimlib/constants.py
manimlib/default_config.yml
manimlib/extract_scene.py
manimlib/logger.py
manimlib/shader_wrapper.py
manimlib/version-config.yaml
manimlib/window.py
manimlib/animation/__init__.py
manimlib/animation/animation.py
manimlib/animation/composition.py
manimlib/animation/creation.py
manimlib/animation/fading.py
manimlib/animation/growing.py
manimlib/animation/indication.py
manimlib/animation/movement.py
manimlib/animation/numbers.py
manimlib/animation/rotation.py
manimlib/animation/specialized.py
manimlib/animation/transform.py
manimlib/animation/transform_matching_parts.py
manimlib/animation/update.py
manimlib/camera/__init__.py
manimlib/camera/camera.py
manimlib/event_handler/__init__.py
manimlib/event_handler/event_dispatcher.py
manimlib/event_handler/event_listner.py
manimlib/event_handler/event_type.py
manimlib/mobject/__init__.py
manimlib/mobject/boolean_ops.py
manimlib/mobject/changing.py
manimlib/mobject/coordinate_systems.py
manimlib/mobject/frame.py
manimlib/mobject/functions.py
manimlib/mobject/geometry.py
manimlib/mobject/interactive.py
manimlib/mobject/matrix.py
manimlib/mobject/mobject.py
manimlib/mobject/mobject_update_utils.py
manimlib/mobject/number_line.py
manimlib/mobject/numbers.py
manimlib/mobject/probability.py
manimlib/mobject/shape_matchers.py
manimlib/mobject/three_dimensions.py
manimlib/mobject/value_tracker.py
manimlib/mobject/vector_field.py
manimlib/mobject/svg/__init__.py
manimlib/mobject/svg/brace.py
manimlib/mobject/svg/drawings.py
manimlib/mobject/svg/svg_mobject.py
manimlib/mobject/svg/tex_mobject.py
manimlib/mobject/svg/text_mobject.py
manimlib/mobject/types/__init__.py
manimlib/mobject/types/dot_cloud.py
manimlib/mobject/types/image_mobject.py
manimlib/mobject/types/point_cloud_mobject.py
manimlib/mobject/types/surface.py
manimlib/mobject/types/vectorized_mobject.py
manimlib/once_useful_constructs/__init__.py
manimlib/once_useful_constructs/arithmetic.py
manim_kunyuan-0.35.dist-info/METADATA
manim_kunyuan-0.35.dist-info/WHEEL
manim_kunyuan-0.35.dist-info/entry_points.txt
manim_kunyuan-0.35.dist-info/top_level.txt
manim_kunyuan-0.35.dist-info/RECORD
